<?xml version="1.0" encoding="UTF-8"?>
<faces-config version="2.2" xmlns="http://xmlns.jcp.org/xml/ns/javaee"
 xmlns:xsi="http://www.w3.org/2001/XMLSchema-instance" xsi:schemaLocation="http://xmlns.jcp.org/xml/ns/javaee http://xmlns.jcp.org/xml/ns/javaee/web-facesconfig_2_2.xsd">
 <navigation-rule>
  <from-view-id>/resources/xhtml/login.xhtml</from-view-id>
  <navigation-case>
   <from-outcome>backoffice</from-outcome>
   <to-view-id>/resources/xhtml/menuBackOffice.xhtml</to-view-id>
  </navigation-case>
    <navigation-case>
   <from-outcome>volver</from-outcome>
   <to-view-id>/resources/xhtml/facturacionBackOffice.xhtml</to-view-id>
  </navigation-case>
  <navigation-case>
   <from-outcome>frontoffice</from-outcome>
   <to-view-id>/resources/xhtml/menuFrontOffice.xhtml</to-view-id>
  </navigation-case>
  <navigation-case>
   <from-outcome>administrador</from-outcome>
   <to-view-id>/resources/xhtml/menuAdmin.xhtml</to-view-id>
  </navigation-case>
  
 </navigation-rule>
 <application/>
</faces-config>
